{
  "total_jobs": 4,
  "total_earned": 0.05160000000000001,
  "average_quality": 0.2957,
  "jobs_by_category": {
    "technical": 1,
    "code": 1,
    "creative": 2
  },
  "history": [
    {
      "timestamp": "2026-01-08T08:15:54.155855",
      "category": "technical",
      "price": 0.0123,
      "quality": 0.2
    },
    {
      "timestamp": "2026-01-08T08:34:41.095042",
      "category": "code",
      "price": 0.0145,
      "quality": 0.9
    },
    {
      "timestamp": "2026-01-08T13:09:04.521210",
      "category": "creative",
      "price": 0.0102,
      "quality": 0.3
    },
    {
      "timestamp": "2026-01-08T18:48:57.354693",
      "category": "creative",
      "price": 0.0146,
      "quality": 0.5
    }
  ]
}